py_ppi_arg/__init__.py
py_ppi_arg/main.py
py_ppi_arg/components/__init__.py
py_ppi_arg/components/client.py
py_ppi_arg/components/enums.py
py_ppi_arg/components/exceptions.py
py_ppi_arg/components/headers.py
py_ppi_arg/components/urls.py
py_ppi_arg-0.1.10.dist-info/METADATA
py_ppi_arg-0.1.10.dist-info/WHEEL
py_ppi_arg-0.1.10.dist-info/top_level.txt
py_ppi_arg-0.1.10.dist-info/RECORD
