Metadata-Version: 2.4
Name: py_ppi_arg
Version: 0.1.10
Summary: Python connector for PortfolioPersonals's Rest APIs.
Home-page: https://github.com/MartinBasualdo0/pyPPI
Author: Martin Basualdo
Author-email: martin.basualdo@hotmail.com
Classifier: Programming Language :: Python :: 3
Classifier: License :: OSI Approved :: MIT License
Classifier: Operating System :: OS Independent
Classifier: Development Status :: 4 - Beta
Classifier: Intended Audience :: Developers
Classifier: Intended Audience :: Information Technology
Classifier: Intended Audience :: Science/Research
Classifier: Topic :: Office/Business :: Financial :: Investment
Classifier: Topic :: Software Development
Requires-Dist: requests>=2.31.0
Requires-Dist: simplejson>=3.19.1
Requires-Dist: pyotp>=2.9.0
Requires-Dist: cloudscraper>=1.2.71
Requires-Dist: beautifulsoup4>=4.12.3
Requires-Dist: bs4>=0.0.2
Dynamic: author
Dynamic: author-email
Dynamic: classifier
Dynamic: description
Dynamic: description-content-type
Dynamic: home-page
Dynamic: requires-dist
Dynamic: summary
